frappe_setup/__init__.py
frappe_setup/cli.py
frappe_setup-0.1.3.dist-info/METADATA
frappe_setup-0.1.3.dist-info/WHEEL
frappe_setup-0.1.3.dist-info/entry_points.txt
frappe_setup-0.1.3.dist-info/top_level.txt
frappe_setup-0.1.3.dist-info/RECORD
